target_args = [daikon.chicory.ChicoryTest]
classpath = '/tmp/markro/daikon/java/lib/checker-framework/checker.jar:/tmp/markro/daikon/java/lib/bcel-6.7.0.jar:/tmp/markro/daikon/java/lib/bcel-util-1.2.1.jar:/tmp/markro/daikon/java/lib/checker-qual.jar:/tmp/markro/daikon/java/lib/commons-exec-1.3.jar:/tmp/markro/daikon/java/lib/daikon-plumelib.jar:/tmp/markro/daikon/java/lib/hamcrest-core-1.3-Daikon.jar:/tmp/markro/daikon/java/lib/hashmap-util-0.0.1.jar:/tmp/markro/daikon/java/lib/java-getopt-1.0.14.0.1.jar:/tmp/markro/daikon/java/lib/junit-4.13.2-Daikon.jar:/tmp/markro/daikon/java/lib/junit-platform-console-standalone-1.9.0-Daikon.jar:/tmp/markro/daikon/java/lib/options-1.0.6.jar:/tmp/markro/daikon/java/lib/plume-util-1.8.1.jar:/tmp/markro/daikon/java/lib/reflection-util-1.0.6.jar:/tmp/markro/daikon/java/lib/require-javadoc-1.0.5-all.jar:/tmp/markro/daikon/java:/homes/gws/markro/jdk8/lib/tools.jar:/homes/gws/markro/jdk8/jre/lib/rt.jar'
path_separator = :

Executing target program: 'java -cp /tmp/markro/daikon/java/lib/checker-framework/checker.jar:/tmp/markro/daikon/java/lib/bcel-6.7.0.jar:/tmp/markro/daikon/java/lib/bcel-util-1.2.1.jar:/tmp/markro/daikon/java/lib/checker-qual.jar:/tmp/markro/daikon/java/lib/commons-exec-1.3.jar:/tmp/markro/daikon/java/lib/daikon-plumelib.jar:/tmp/markro/daikon/java/lib/hamcrest-core-1.3-Daikon.jar:/tmp/markro/daikon/java/lib/hashmap-util-0.0.1.jar:/tmp/markro/daikon/java/lib/java-getopt-1.0.14.0.1.jar:/tmp/markro/daikon/java/lib/junit-4.13.2-Daikon.jar:/tmp/markro/daikon/java/lib/junit-platform-console-standalone-1.9.0-Daikon.jar:/tmp/markro/daikon/java/lib/options-1.0.6.jar:/tmp/markro/daikon/java/lib/plume-util-1.8.1.jar:/tmp/markro/daikon/java/lib/reflection-util-1.0.6.jar:/tmp/markro/daikon/java/lib/require-javadoc-1.0.5-all.jar:/tmp/markro/daikon/java:/homes/gws/markro/jdk8/lib/tools.jar:/homes/gws/markro/jdk8/jre/lib/rt.jar -ea -esa -Xmx3600m '-javaagent:/tmp/markro/daikon/java/ChicoryPremain.jar=--verbose --debug --dtrace-file=ChicoryTest.dtrace.gz daikon.chicory.ChicoryTest
In Chicory premain, agentargs ='--verbose --debug --dtrace-file=ChicoryTest.dtrace.gz', Instrumentation = 'sun.instrument.InstrumentationImpl@54bedef2'Options settings: 
help                             = false
verbose                          = true
debug                            = true
dtrace-file                      = ChicoryTest.dtrace.gz
comparability-file               = null
output-dir                       = .
config-dir                       = null
daikon                           = false
daikon-online                    = false
daikon-args                      = 
heap-size                        = 3600m
premain                          = null
ppt-select-pattern               = []
ppt-omit-pattern                 = []
sample-start                     = 0
boot-classes                     = null
instrument-clinit                = false
nesting-depth                    = 2
omit-var                         = null
std-visibility                   = false
purity-file                      = null
debug-transform                  = false
debug-decl-print                 = false
debug-ppt-names                  = false
daikon-port                      = -1
debug-runtime                    = false
entered daikon.chicory.Runtime.setDtrace(./ChicoryTest.dtrace.gz, false)...
Classloader of transformer = sun.misc.Launcher$AppClassLoader@18b4aac2
call addTransformer
exit premain

Method = void <init>()
arg_types(0): 
arg_names(0): 
localvars(1): this 
Original code: Code(maxStack = 2, maxLocals = 1, code_length = 11)
0:    aload_0
1:    invokespecial	java.lang.Object.<init> ()V (1)
4:    aload_0
5:    bipush		55
7:    putfield		daikon.chicory.ChicoryTest.t1 I (2)
10:   return

Attribute(s) = 
LocalVariableTable:
LocalVariable(startPc = 0, length = 11, index = 0:daikon.chicory.ChicoryTest this)
LineNumberTable:
LineNumber(0, 7), LineNumber(4, 9)


StackMap(Original) 0 items:
Added <this> 0: this, daikon.chicory.ChicoryTest
create_method_info1 0
create_method_info2 0
Looking for exit points in <init>
Exit at line 9

StackMap(After create_method_info) 0 items:
Added local  1: this_invocation_nonce, int
New LocalVariableTable:
LocalVariable(startPc = 0, length = 11, index = 0:daikon.chicory.ChicoryTest this)
LocalVariable(startPc = 0, length = 11, index = 1:int this_invocation_nonce)

StackMap(After cln) 0 items:
Modified code: Code(maxStack = 2, maxLocals = 2, code_length = 11)
0:    aload_0
1:    invokespecial	java.lang.Object.<init> ()V (1)
4:    aload_0
5:    bipush		55
7:    putfield		daikon.chicory.ChicoryTest.t1 I (2)
10:   return

Attribute(s) = 
LocalVariableTable:
LocalVariable(startPc = 0, length = 11, index = 0:daikon.chicory.ChicoryTest this)
LocalVariable(startPc = 0, length = 11, index = 1:int this_invocation_nonce)
LineNumberTable:
LineNumber(0, 7), LineNumber(4, 9)
method '<init>' is a constructor

StackMap(After add_entry_instrumentation) 2 items:
@007 (APPEND 1, offset delta=7, locals={(type=Integer)}) 
@017 (SAME, offset delta=9) 
Modified code: Code(maxStack = 2, maxLocals = 2, code_length = 28)
0:    getstatic		daikon.chicory.Runtime.nonce Ljava/util/concurrent/atomic/AtomicInteger; (109)
3:    invokevirtual	java.util.concurrent.atomic.AtomicInteger.getAndIncrement ()I (115)
6:    istore_1
7:    aconst_null
8:    iload_1
9:    iconst_0
10:   iconst_0
11:   anewarray		<java.lang.Object> (8)
14:   invokestatic	daikon.chicory.Runtime.enter (Ljava/lang/Object;II[Ljava/lang/Object;)V (119)
17:   aload_0
18:   invokespecial	java.lang.Object.<init> ()V (1)
21:   aload_0
22:   bipush		55
24:   putfield		daikon.chicory.ChicoryTest.t1 I (2)
27:   return

Attribute(s) = 
LocalVariableTable:
LocalVariable(startPc = 0, length = 28, index = 0:daikon.chicory.ChicoryTest this)
LocalVariable(startPc = 0, length = 28, index = 1:int this_invocation_nonce)
LineNumberTable:
LineNumber(0, 7), LineNumber(21, 9)

StackMap(Before insert_inst) 2 items:
@007 (APPEND 1, offset delta=7, locals={(type=Integer)}) 
@017 (SAME, offset delta=9) 
inst:   27: return[177](1) 
targeter: LocalVariableGen(this, daikon.chicory.ChicoryTest,    0: getstatic[178](3) 109,   27: return[177](1)) 
targeter: LocalVariableGen(this_invocation_nonce, int,    0: getstatic[178](3) 109,   27: return[177](1)) 
  insert_inst: 8
   0: aload_0[42](1)
   1: iload_1[27](1)
   2: iconst_0[3](1)
   3: iconst_0[3](1)
   4: anewarray[189](3) 8
   7: aconst_null[1](1)
   8: bipush[16](2) 9
  10: invokestatic[184](3) 123

  ih:   27: return[177](1)

StackMap(After updateStackMapOffset) 2 items:
@007 (APPEND 1, offset delta=7, locals={(type=Integer)}) 
@017 (SAME, offset delta=9) 
inst:   27: aload_0[42](1) 
inst:   28: iload_1[27](1) 
inst:   29: iconst_0[3](1) 
inst:   30: iconst_0[3](1) 
inst:   31: anewarray[189](3) 8 
inst:   34: aconst_null[1](1) 
inst:   35: bipush[16](2) 9 
inst:   37: invokestatic[184](3) 123 
inst:   40: return[177](1) 
targeter: LocalVariableGen(this, daikon.chicory.ChicoryTest,    0: getstatic[178](3) 109,   40: return[177](1)) 
targeter: LocalVariableGen(this_invocation_nonce, int,    0: getstatic[178](3) 109,   40: return[177](1)) 

StackMap(Final) 2 items:
@007 (APPEND 1, offset delta=7, locals={(type=Integer)}) 
@017 (SAME, offset delta=9) 
Modified code: Code(maxStack = 6, maxLocals = 2, code_length = 41)
0:    getstatic		daikon.chicory.Runtime.nonce Ljava/util/concurrent/atomic/AtomicInteger; (109)
3:    invokevirtual	java.util.concurrent.atomic.AtomicInteger.getAndIncrement ()I (115)
6:    istore_1
7:    aconst_null
8:    iload_1
9:    iconst_0
10:   iconst_0
11:   anewarray		<java.lang.Object> (8)
14:   invokestatic	daikon.chicory.Runtime.enter (Ljava/lang/Object;II[Ljava/lang/Object;)V (119)
17:   aload_0
18:   invokespecial	java.lang.Object.<init> ()V (1)
21:   aload_0
22:   bipush		55
24:   putfield		daikon.chicory.ChicoryTest.t1 I (2)
27:   aload_0
28:   iload_1
29:   iconst_0
30:   iconst_0
31:   anewarray		<java.lang.Object> (8)
34:   aconst_null
35:   bipush		9
37:   invokestatic	daikon.chicory.Runtime.exit (Ljava/lang/Object;II[Ljava/lang/Object;Ljava/lang/Object;I)V (123)
40:   return

Attribute(s) = 
StackMapTable:
StackMap(
@007 (APPEND 1, offset delta=7, locals={(type=Integer)}), 
@017 (SAME, offset delta=9))
LocalVariableTable:
LocalVariable(startPc = 0, length = 41, index = 0:daikon.chicory.ChicoryTest this)
LocalVariable(startPc = 0, length = 41, index = 1:int this_invocation_nonce)
LineNumberTable:
LineNumber(0, 7), LineNumber(21, 9)
Attribute Index: 57 Name: StackMapTable
Attribute Index: 34 Name: LocalVariableTable
Attribute Index: 33 Name: LineNumberTable

Method = public static void main(String[] args)
arg_types(1): java.lang.String[] 
arg_names(1): arg0 
localvars(4): args t i d 
Original code: Code(maxStack = 6, maxLocals = 5, code_length = 107)
0:    new		<daikon.chicory.ChicoryTest> (3)
3:    dup
4:    invokespecial	daikon.chicory.ChicoryTest.<init> ()V (4)
7:    astore_1
8:    aload_1
9:    iconst_5
10:   putfield		daikon.chicory.ChicoryTest.t1 I (2)
13:   aload_1
14:   iconst_0
15:   invokevirtual	daikon.chicory.ChicoryTest.sample (I)I (5)
18:   istore_2
19:   getstatic		java.lang.System.out Ljava/io/PrintStream; (6)
22:   ldc		"sample return [35]   = %d%n" (7)
24:   iconst_1
25:   anewarray		<java.lang.Object> (8)
28:   dup
29:   iconst_0
30:   iload_2
31:   invokestatic	java.lang.Integer.valueOf (I)Ljava/lang/Integer; (9)
34:   aastore
35:   invokevirtual	java.io.PrintStream.format (Ljava/lang/String;[Ljava/lang/Object;)Ljava/io/PrintStream; (10)
38:   pop
39:   aload_1
40:   invokevirtual	daikon.chicory.ChicoryTest.sample1 ()Ldaikon/chicory/ChicoryTest; (11)
43:   astore_1
44:   getstatic		java.lang.System.out Ljava/io/PrintStream; (6)
47:   ldc		"sample return [32]   = %d%n" (12)
49:   iconst_1
50:   anewarray		<java.lang.Object> (8)
53:   dup
54:   iconst_0
55:   aload_1
56:   getfield		daikon.chicory.ChicoryTest.t1 I (2)
59:   invokestatic	java.lang.Integer.valueOf (I)Ljava/lang/Integer; (9)
62:   aastore
63:   invokevirtual	java.io.PrintStream.format (Ljava/lang/String;[Ljava/lang/Object;)Ljava/io/PrintStream; (10)
66:   pop
67:   aload_1
68:   invokevirtual	daikon.chicory.ChicoryTest.sample2 ()D (13)
71:   dstore_3
72:   getstatic		java.lang.System.out Ljava/io/PrintStream; (6)
75:   new		<java.lang.StringBuilder> (14)
78:   dup
79:   invokespecial	java.lang.StringBuilder.<init> ()V (15)
82:   ldc		"sample return [62.4] = " (16)
84:   invokevirtual	java.lang.StringBuilder.append (Ljava/lang/String;)Ljava/lang/StringBuilder; (17)
87:   dload_3
88:   invokevirtual	java.lang.StringBuilder.append (D)Ljava/lang/StringBuilder; (18)
91:   invokevirtual	java.lang.StringBuilder.toString ()Ljava/lang/String; (19)
94:   invokevirtual	java.io.PrintStream.println (Ljava/lang/String;)V (20)
97:   aload_1
98:   dconst_1
99:   ldc2_w		5.0 (21)
102:  invokevirtual	daikon.chicory.ChicoryTest.test_d (DD)D (23)
105:  pop2
106:  return

Attribute(s) = 
LocalVariableTable:
LocalVariable(startPc = 0, length = 107, index = 0:java.lang.String[] args)
LocalVariable(startPc = 8, length = 99, index = 1:daikon.chicory.ChicoryTest t)
LocalVariable(startPc = 19, length = 88, index = 2:int i)
LocalVariable(startPc = 72, length = 35, index = 3:double d)
LineNumberTable:
LineNumber(0, 13), LineNumber(8, 14), LineNumber(13, 15), LineNumber(19, 16), 
LineNumber(39, 18), LineNumber(44, 19), LineNumber(67, 21), LineNumber(72, 22), 
LineNumber(97, 24), LineNumber(106, 25)


StackMap(Original) 0 items:
Added param  0: args, java.lang.String[]
Added local  1: t, daikon.chicory.ChicoryTest
Added local  2: i, int
Added local  3: d, double
create_method_info1 1
arg: arg0
create_method_info2 1
arg: args
Looking for exit points in main
Exit at line 25

StackMap(After create_method_info) 0 items:
Added local  1: this_invocation_nonce, int
New LocalVariableTable:
LocalVariable(startPc = 0, length = 109, index = 0:java.lang.String[] args)
LocalVariable(startPc = 0, length = 109, index = 1:int this_invocation_nonce)
LocalVariable(startPc = 8, length = 100, index = 2:daikon.chicory.ChicoryTest t)
LocalVariable(startPc = 19, length = 89, index = 3:int i)
LocalVariable(startPc = 73, length = 35, index = 4:double d)

StackMap(After cln) 0 items:
Modified code: Code(maxStack = 6, maxLocals = 6, code_length = 109)
0:    new		<daikon.chicory.ChicoryTest> (3)
3:    dup
4:    invokespecial	daikon.chicory.ChicoryTest.<init> ()V (4)
7:    astore_2
8:    aload_2
9:    iconst_5
10:   putfield		daikon.chicory.ChicoryTest.t1 I (2)
13:   aload_2
14:   iconst_0
15:   invokevirtual	daikon.chicory.ChicoryTest.sample (I)I (5)
18:   istore_3
19:   getstatic		java.lang.System.out Ljava/io/PrintStream; (6)
22:   ldc		"sample return [35]   = %d%n" (7)
24:   iconst_1
25:   anewarray		<java.lang.Object> (8)
28:   dup
29:   iconst_0
30:   iload_3
31:   invokestatic	java.lang.Integer.valueOf (I)Ljava/lang/Integer; (9)
34:   aastore
35:   invokevirtual	java.io.PrintStream.format (Ljava/lang/String;[Ljava/lang/Object;)Ljava/io/PrintStream; (10)
38:   pop
39:   aload_2
40:   invokevirtual	daikon.chicory.ChicoryTest.sample1 ()Ldaikon/chicory/ChicoryTest; (11)
43:   astore_2
44:   getstatic		java.lang.System.out Ljava/io/PrintStream; (6)
47:   ldc		"sample return [32]   = %d%n" (12)
49:   iconst_1
50:   anewarray		<java.lang.Object> (8)
53:   dup
54:   iconst_0
55:   aload_2
56:   getfield		daikon.chicory.ChicoryTest.t1 I (2)
59:   invokestatic	java.lang.Integer.valueOf (I)Ljava/lang/Integer; (9)
62:   aastore
63:   invokevirtual	java.io.PrintStream.format (Ljava/lang/String;[Ljava/lang/Object;)Ljava/io/PrintStream; (10)
66:   pop
67:   aload_2
68:   invokevirtual	daikon.chicory.ChicoryTest.sample2 ()D (13)
71:   dstore		%4
73:   getstatic		java.lang.System.out Ljava/io/PrintStream; (6)
76:   new		<java.lang.StringBuilder> (14)
79:   dup
80:   invokespecial	java.lang.StringBuilder.<init> ()V (15)
83:   ldc		"sample return [62.4] = " (16)
85:   invokevirtual	java.lang.StringBuilder.append (Ljava/lang/String;)Ljava/lang/StringBuilder; (17)
88:   dload		%4
90:   invokevirtual	java.lang.StringBuilder.append (D)Ljava/lang/StringBuilder; (18)
93:   invokevirtual	java.lang.StringBuilder.toString ()Ljava/lang/String; (19)
96:   invokevirtual	java.io.PrintStream.println (Ljava/lang/String;)V (20)
99:   aload_2
100:  dconst_1
101:  ldc2_w		5.0 (21)
104:  invokevirtual	daikon.chicory.ChicoryTest.test_d (DD)D (23)
107:  pop2
108:  return

Attribute(s) = 
LocalVariableTable:
LocalVariable(startPc = 0, length = 109, index = 0:java.lang.String[] args)
LocalVariable(startPc = 0, length = 109, index = 1:int this_invocation_nonce)
LocalVariable(startPc = 8, length = 100, index = 2:daikon.chicory.ChicoryTest t)
LocalVariable(startPc = 19, length = 89, index = 3:int i)
LocalVariable(startPc = 73, length = 35, index = 4:double d)
LineNumberTable:
LineNumber(0, 13), LineNumber(8, 14), LineNumber(13, 15), LineNumber(19, 16), 
LineNumber(39, 18), LineNumber(44, 19), LineNumber(67, 21), LineNumber(73, 22), 
LineNumber(99, 24), LineNumber(108, 25)

StackMap(After add_entry_instrumentation) 2 items:
@007 (APPEND 1, offset delta=7, locals={(type=Integer)}) 
@021 (SAME, offset delta=13) 
Modified code: Code(maxStack = 6, maxLocals = 6, code_length = 130)
0:    getstatic		daikon.chicory.Runtime.nonce Ljava/util/concurrent/atomic/AtomicInteger; (109)
3:    invokevirtual	java.util.concurrent.atomic.AtomicInteger.getAndIncrement ()I (115)
6:    istore_1
7:    aconst_null
8:    iload_1
9:    iconst_1
10:   iconst_1
11:   anewarray		<java.lang.Object> (8)
14:   dup
15:   iconst_0
16:   aload_0
17:   aastore
18:   invokestatic	daikon.chicory.Runtime.enter (Ljava/lang/Object;II[Ljava/lang/Object;)V (119)
21:   new		<daikon.chicory.ChicoryTest> (3)
24:   dup
25:   invokespecial	daikon.chicory.ChicoryTest.<init> ()V (4)
28:   astore_2
29:   aload_2
30:   iconst_5
31:   putfield		daikon.chicory.ChicoryTest.t1 I (2)
34:   aload_2
35:   iconst_0
36:   invokevirtual	daikon.chicory.ChicoryTest.sample (I)I (5)
39:   istore_3
40:   getstatic		java.lang.System.out Ljava/io/PrintStream; (6)
43:   ldc		"sample return [35]   = %d%n" (7)
45:   iconst_1
46:   anewarray		<java.lang.Object> (8)
49:   dup
50:   iconst_0
51:   iload_3
52:   invokestatic	java.lang.Integer.valueOf (I)Ljava/lang/Integer; (9)
55:   aastore
56:   invokevirtual	java.io.PrintStream.format (Ljava/lang/String;[Ljava/lang/Object;)Ljava/io/PrintStream; (10)
59:   pop
60:   aload_2
61:   invokevirtual	daikon.chicory.ChicoryTest.sample1 ()Ldaikon/chicory/ChicoryTest; (11)
64:   astore_2
65:   getstatic		java.lang.System.out Ljava/io/PrintStream; (6)
68:   ldc		"sample return [32]   = %d%n" (12)
70:   iconst_1
71:   anewarray		<java.lang.Object> (8)
74:   dup
75:   iconst_0
76:   aload_2
77:   getfield		daikon.chicory.ChicoryTest.t1 I (2)
80:   invokestatic	java.lang.Integer.valueOf (I)Ljava/lang/Integer; (9)
83:   aastore
84:   invokevirtual	java.io.PrintStream.format (Ljava/lang/String;[Ljava/lang/Object;)Ljava/io/PrintStream; (10)
87:   pop
88:   aload_2
89:   invokevirtual	daikon.chicory.ChicoryTest.sample2 ()D (13)
92:   dstore		%4
94:   getstatic		java.lang.System.out Ljava/io/PrintStream; (6)
97:   new		<java.lang.StringBuilder> (14)
100:  dup
101:  invokespecial	java.lang.StringBuilder.<init> ()V (15)
104:  ldc		"sample return [62.4] = " (16)
106:  invokevirtual	java.lang.StringBuilder.append (Ljava/lang/String;)Ljava/lang/StringBuilder; (17)
109:  dload		%4
111:  invokevirtual	java.lang.StringBuilder.append (D)Ljava/lang/StringBuilder; (18)
114:  invokevirtual	java.lang.StringBuilder.toString ()Ljava/lang/String; (19)
117:  invokevirtual	java.io.PrintStream.println (Ljava/lang/String;)V (20)
120:  aload_2
121:  dconst_1
122:  ldc2_w		5.0 (21)
125:  invokevirtual	daikon.chicory.ChicoryTest.test_d (DD)D (23)
128:  pop2
129:  return

Attribute(s) = 
LocalVariableTable:
LocalVariable(startPc = 0, length = 130, index = 0:java.lang.String[] args)
LocalVariable(startPc = 0, length = 130, index = 1:int this_invocation_nonce)
LocalVariable(startPc = 29, length = 100, index = 2:daikon.chicory.ChicoryTest t)
LocalVariable(startPc = 40, length = 89, index = 3:int i)
LocalVariable(startPc = 94, length = 35, index = 4:double d)
LineNumberTable:
LineNumber(0, 13), LineNumber(29, 14), LineNumber(34, 15), LineNumber(40, 16), 
LineNumber(60, 18), LineNumber(65, 19), LineNumber(88, 21), LineNumber(94, 22), 
LineNumber(120, 24), LineNumber(129, 25)

StackMap(Before insert_inst) 2 items:
@007 (APPEND 1, offset delta=7, locals={(type=Integer)}) 
@021 (SAME, offset delta=13) 
inst:  129: return[177](1) 
targeter: LocalVariableGen(this_invocation_nonce, int,    0: getstatic[178](3) 109,  129: return[177](1)) 
targeter: LocalVariableGen(i, int,   40: getstatic[178](3) 6,  129: return[177](1)) 
targeter: LocalVariableGen(d, double,   94: getstatic[178](3) 6,  129: return[177](1)) 
targeter: org.apache.bcel.generic.LineNumberGen@12843fce 
targeter: LocalVariableGen(args, java.lang.String[],    0: getstatic[178](3) 109,  129: return[177](1)) 
targeter: LocalVariableGen(t, daikon.chicory.ChicoryTest,   29: aload_2[44](1),  129: return[177](1)) 
  insert_inst: 12
   0: aconst_null[1](1)
   1: iload_1[27](1)
   2: iconst_1[4](1)
   3: iconst_1[4](1)
   4: anewarray[189](3) 8
   7: dup[89](1)
   8: iconst_0[3](1)
   9: aload_0[42](1)
  10: aastore[83](1)
  11: aconst_null[1](1)
  12: bipush[16](2) 25
  14: invokestatic[184](3) 123

  ih:  129: return[177](1)

StackMap(After updateStackMapOffset) 2 items:
@007 (APPEND 1, offset delta=7, locals={(type=Integer)}) 
@021 (SAME, offset delta=13) 
inst:  129: aconst_null[1](1) 
targeter: org.apache.bcel.generic.LineNumberGen@12843fce 
inst:  130: iload_1[27](1) 
inst:  131: iconst_1[4](1) 
inst:  132: iconst_1[4](1) 
inst:  133: anewarray[189](3) 8 
inst:  136: dup[89](1) 
inst:  137: iconst_0[3](1) 
inst:  138: aload_0[42](1) 
inst:  139: aastore[83](1) 
inst:  140: aconst_null[1](1) 
inst:  141: bipush[16](2) 25 
inst:  143: invokestatic[184](3) 123 
inst:  146: return[177](1) 
targeter: LocalVariableGen(this_invocation_nonce, int,    0: getstatic[178](3) 109,  146: return[177](1)) 
targeter: LocalVariableGen(i, int,   40: getstatic[178](3) 6,  146: return[177](1)) 
targeter: LocalVariableGen(d, double,   94: getstatic[178](3) 6,  146: return[177](1)) 
targeter: LocalVariableGen(args, java.lang.String[],    0: getstatic[178](3) 109,  146: return[177](1)) 
targeter: LocalVariableGen(t, daikon.chicory.ChicoryTest,   29: aload_2[44](1),  146: return[177](1)) 

StackMap(Final) 2 items:
@007 (APPEND 1, offset delta=7, locals={(type=Integer)}) 
@021 (SAME, offset delta=13) 
Modified code: Code(maxStack = 7, maxLocals = 6, code_length = 147)
0:    getstatic		daikon.chicory.Runtime.nonce Ljava/util/concurrent/atomic/AtomicInteger; (109)
3:    invokevirtual	java.util.concurrent.atomic.AtomicInteger.getAndIncrement ()I (115)
6:    istore_1
7:    aconst_null
8:    iload_1
9:    iconst_1
10:   iconst_1
11:   anewarray		<java.lang.Object> (8)
14:   dup
15:   iconst_0
16:   aload_0
17:   aastore
18:   invokestatic	daikon.chicory.Runtime.enter (Ljava/lang/Object;II[Ljava/lang/Object;)V (119)
21:   new		<daikon.chicory.ChicoryTest> (3)
24:   dup
25:   invokespecial	daikon.chicory.ChicoryTest.<init> ()V (4)
28:   astore_2
29:   aload_2
30:   iconst_5
31:   putfield		daikon.chicory.ChicoryTest.t1 I (2)
34:   aload_2
35:   iconst_0
36:   invokevirtual	daikon.chicory.ChicoryTest.sample (I)I (5)
39:   istore_3
40:   getstatic		java.lang.System.out Ljava/io/PrintStream; (6)
43:   ldc		"sample return [35]   = %d%n" (7)
45:   iconst_1
46:   anewarray		<java.lang.Object> (8)
49:   dup
50:   iconst_0
51:   iload_3
52:   invokestatic	java.lang.Integer.valueOf (I)Ljava/lang/Integer; (9)
55:   aastore
56:   invokevirtual	java.io.PrintStream.format (Ljava/lang/String;[Ljava/lang/Object;)Ljava/io/PrintStream; (10)
59:   pop
60:   aload_2
61:   invokevirtual	daikon.chicory.ChicoryTest.sample1 ()Ldaikon/chicory/ChicoryTest; (11)
64:   astore_2
65:   getstatic		java.lang.System.out Ljava/io/PrintStream; (6)
68:   ldc		"sample return [32]   = %d%n" (12)
70:   iconst_1
71:   anewarray		<java.lang.Object> (8)
74:   dup
75:   iconst_0
76:   aload_2
77:   getfield		daikon.chicory.ChicoryTest.t1 I (2)
80:   invokestatic	java.lang.Integer.valueOf (I)Ljava/lang/Integer; (9)
83:   aastore
84:   invokevirtual	java.io.PrintStream.format (Ljava/lang/String;[Ljava/lang/Object;)Ljava/io/PrintStream; (10)
87:   pop
88:   aload_2
89:   invokevirtual	daikon.chicory.ChicoryTest.sample2 ()D (13)
92:   dstore		%4
94:   getstatic		java.lang.System.out Ljava/io/PrintStream; (6)
97:   new		<java.lang.StringBuilder> (14)
100:  dup
101:  invokespecial	java.lang.StringBuilder.<init> ()V (15)
104:  ldc		"sample return [62.4] = " (16)
106:  invokevirtual	java.lang.StringBuilder.append (Ljava/lang/String;)Ljava/lang/StringBuilder; (17)
109:  dload		%4
111:  invokevirtual	java.lang.StringBuilder.append (D)Ljava/lang/StringBuilder; (18)
114:  invokevirtual	java.lang.StringBuilder.toString ()Ljava/lang/String; (19)
117:  invokevirtual	java.io.PrintStream.println (Ljava/lang/String;)V (20)
120:  aload_2
121:  dconst_1
122:  ldc2_w		5.0 (21)
125:  invokevirtual	daikon.chicory.ChicoryTest.test_d (DD)D (23)
128:  pop2
129:  aconst_null
130:  iload_1
131:  iconst_1
132:  iconst_1
133:  anewarray		<java.lang.Object> (8)
136:  dup
137:  iconst_0
138:  aload_0
139:  aastore
140:  aconst_null
141:  bipush		25
143:  invokestatic	daikon.chicory.Runtime.exit (Ljava/lang/Object;II[Ljava/lang/Object;Ljava/lang/Object;I)V (123)
146:  return

Attribute(s) = 
StackMapTable:
StackMap(
@007 (APPEND 1, offset delta=7, locals={(type=Integer)}), 
@021 (SAME, offset delta=13))
LocalVariableTable:
LocalVariable(startPc = 0, length = 147, index = 0:java.lang.String[] args)
LocalVariable(startPc = 0, length = 147, index = 1:int this_invocation_nonce)
LocalVariable(startPc = 29, length = 117, index = 2:daikon.chicory.ChicoryTest t)
LocalVariable(startPc = 40, length = 106, index = 3:int i)
LocalVariable(startPc = 94, length = 52, index = 4:double d)
LineNumberTable:
LineNumber(0, 13), LineNumber(29, 14), LineNumber(34, 15), LineNumber(40, 16), 
LineNumber(60, 18), LineNumber(65, 19), LineNumber(88, 21), LineNumber(94, 22), 
LineNumber(120, 24), LineNumber(129, 25)
Attribute Index: 57 Name: StackMapTable
Attribute Index: 34 Name: LocalVariableTable
Attribute Index: 33 Name: LineNumberTable

Method = public daikon.chicory.ChicoryTest[] test_array() [(Unknown attribute RuntimeVisibleTypeAnnotations: 00 01 14 00 00 30 00 00)]
arg_types(0): 
arg_names(0): 
localvars(1): this 
Original code: Code(maxStack = 1, maxLocals = 1, code_length = 2)
0:    aconst_null
1:    areturn

Attribute(s) = 
LocalVariableTable:
LocalVariable(startPc = 0, length = 2, index = 0:daikon.chicory.ChicoryTest this)
LineNumberTable:
LineNumber(0, 28)


StackMap(Original) 0 items:
Added <this> 0: this, daikon.chicory.ChicoryTest
create_method_info1 0
create_method_info2 0
Looking for exit points in test_array
Exit at line 28

StackMap(After create_method_info) 0 items:
Added local  1: this_invocation_nonce, int
New LocalVariableTable:
LocalVariable(startPc = 0, length = 2, index = 0:daikon.chicory.ChicoryTest this)
LocalVariable(startPc = 0, length = 2, index = 1:int this_invocation_nonce)

StackMap(After cln) 0 items:
Modified code: Code(maxStack = 1, maxLocals = 2, code_length = 2)
0:    aconst_null
1:    areturn

Attribute(s) = 
LocalVariableTable:
LocalVariable(startPc = 0, length = 2, index = 0:daikon.chicory.ChicoryTest this)
LocalVariable(startPc = 0, length = 2, index = 1:int this_invocation_nonce)
LineNumberTable:
LineNumber(0, 28)

StackMap(After add_entry_instrumentation) 2 items:
@007 (APPEND 1, offset delta=7, locals={(type=Integer)}) 
@017 (SAME, offset delta=9) 
Modified code: Code(maxStack = 1, maxLocals = 2, code_length = 19)
0:    getstatic		daikon.chicory.Runtime.nonce Ljava/util/concurrent/atomic/AtomicInteger; (109)
3:    invokevirtual	java.util.concurrent.atomic.AtomicInteger.getAndIncrement ()I (115)
6:    istore_1
7:    aload_0
8:    iload_1
9:    iconst_2
10:   iconst_0
11:   anewarray		<java.lang.Object> (8)
14:   invokestatic	daikon.chicory.Runtime.enter (Ljava/lang/Object;II[Ljava/lang/Object;)V (119)
17:   aconst_null
18:   areturn

Attribute(s) = 
LocalVariableTable:
LocalVariable(startPc = 0, length = 19, index = 0:daikon.chicory.ChicoryTest this)
LocalVariable(startPc = 0, length = 19, index = 1:int this_invocation_nonce)
LineNumberTable:
LineNumber(0, 28)
Adding return local of type daikon.chicory.ChicoryTest[]

StackMap(Before insert_inst) 2 items:
@007 (APPEND 1, offset delta=7, locals={(type=Integer)}) 
@017 (SAME, offset delta=9) 
inst:   18: areturn[176](1) 
targeter: LocalVariableGen(this, daikon.chicory.ChicoryTest,    0: getstatic[178](3) 109,   18: areturn[176](1)) 
targeter: LocalVariableGen(this_invocation_nonce, int,    0: getstatic[178](3) 109,   18: areturn[176](1)) 
targeter: LocalVariableGen(return__$trace2_val, daikon.chicory.ChicoryTest[],    0: getstatic[178](3) 109,   18: areturn[176](1)) 
  insert_inst: 10
   0: dup[89](1)
   1: astore_2[77](1)
   2: aload_0[42](1)
   3: iload_1[27](1)
   4: iconst_2[5](1)
   5: iconst_0[3](1)
   6: anewarray[189](3) 8
   9: aload_2[44](1)
  10: bipush[16](2) 28
  12: invokestatic[184](3) 123

  ih:   18: areturn[176](1)

StackMap(After updateStackMapOffset) 2 items:
@007 (APPEND 1, offset delta=7, locals={(type=Integer)}) 
@017 (SAME, offset delta=9) 
inst:   18: dup[89](1) 
inst:   19: astore_2[77](1) 
inst:   20: aload_0[42](1) 
inst:   21: iload_1[27](1) 
inst:   22: iconst_2[5](1) 
inst:   23: iconst_0[3](1) 
inst:   24: anewarray[189](3) 8 
inst:   27: aload_2[44](1) 
inst:   28: bipush[16](2) 28 
inst:   30: invokestatic[184](3) 123 
inst:   33: areturn[176](1) 
targeter: LocalVariableGen(this, daikon.chicory.ChicoryTest,    0: getstatic[178](3) 109,   33: areturn[176](1)) 
targeter: LocalVariableGen(this_invocation_nonce, int,    0: getstatic[178](3) 109,   33: areturn[176](1)) 
targeter: LocalVariableGen(return__$trace2_val, daikon.chicory.ChicoryTest[],    0: getstatic[178](3) 109,   33: areturn[176](1)) 

StackMap(Final) 2 items:
@007 (APPEND 1, offset delta=7, locals={(type=Integer)}) 
@017 (SAME, offset delta=9) 
Modified code: Code(maxStack = 7, maxLocals = 3, code_length = 34)
0:    getstatic		daikon.chicory.Runtime.nonce Ljava/util/concurrent/atomic/AtomicInteger; (109)
3:    invokevirtual	java.util.concurrent.atomic.AtomicInteger.getAndIncrement ()I (115)
6:    istore_1
7:    aload_0
8:    iload_1
9:    iconst_2
10:   iconst_0
11:   anewarray		<java.lang.Object> (8)
14:   invokestatic	daikon.chicory.Runtime.enter (Ljava/lang/Object;II[Ljava/lang/Object;)V (119)
17:   aconst_null
18:   dup
19:   astore_2
20:   aload_0
21:   iload_1
22:   iconst_2
23:   iconst_0
24:   anewarray		<java.lang.Object> (8)
27:   aload_2
28:   bipush		28
30:   invokestatic	daikon.chicory.Runtime.exit (Ljava/lang/Object;II[Ljava/lang/Object;Ljava/lang/Object;I)V (123)
33:   areturn

Attribute(s) = 
StackMapTable:
StackMap(
@007 (APPEND 1, offset delta=7, locals={(type=Integer)}), 
@017 (SAME, offset delta=9))
LocalVariableTable:
LocalVariable(startPc = 0, length = 34, index = 0:daikon.chicory.ChicoryTest this)
LocalVariable(startPc = 0, length = 34, index = 1:int this_invocation_nonce)
LocalVariable(startPc = 0, length = 34, index = 2:daikon.chicory.ChicoryTest[] return__$trace2_val)
LineNumberTable:
LineNumber(0, 28)
Attribute Index: 57 Name: StackMapTable
Attribute Index: 34 Name: LocalVariableTable
Attribute Index: 33 Name: LineNumberTable

Method = public double test_d(double d1, double d2)
arg_types(2): double double 
arg_names(2): arg0 arg1 
localvars(3): this d1 d2 
Original code: Code(maxStack = 4, maxLocals = 5, code_length = 4)
0:    dload_1
1:    dload_3
2:    dmul
3:    dreturn

Attribute(s) = 
LocalVariableTable:
LocalVariable(startPc = 0, length = 4, index = 0:daikon.chicory.ChicoryTest this)
LocalVariable(startPc = 0, length = 4, index = 1:double d1)
LocalVariable(startPc = 0, length = 4, index = 3:double d2)
LineNumberTable:
LineNumber(0, 32)


StackMap(Original) 0 items:
Added <this> 0: this, daikon.chicory.ChicoryTest
Added param  1: d1, double
Added param  3: d2, double
create_method_info1 2
arg: arg0
arg: arg1
create_method_info2 2
arg: d1
arg: d2
Looking for exit points in test_d
Exit at line 32

StackMap(After create_method_info) 0 items:
Added local  5: this_invocation_nonce, int
New LocalVariableTable:
LocalVariable(startPc = 0, length = 4, index = 0:daikon.chicory.ChicoryTest this)
LocalVariable(startPc = 0, length = 4, index = 1:double d1)
LocalVariable(startPc = 0, length = 4, index = 3:double d2)
LocalVariable(startPc = 0, length = 4, index = 5:int this_invocation_nonce)

StackMap(After cln) 0 items:
Modified code: Code(maxStack = 4, maxLocals = 6, code_length = 4)
0:    dload_1
1:    dload_3
2:    dmul
3:    dreturn

Attribute(s) = 
LocalVariableTable:
LocalVariable(startPc = 0, length = 4, index = 0:daikon.chicory.ChicoryTest this)
LocalVariable(startPc = 0, length = 4, index = 1:double d1)
LocalVariable(startPc = 0, length = 4, index = 3:double d2)
LocalVariable(startPc = 0, length = 4, index = 5:int this_invocation_nonce)
LineNumberTable:
LineNumber(0, 32)

StackMap(After add_entry_instrumentation) 2 items:
@008 (APPEND 1, offset delta=8, locals={(type=Integer)}) 
@041 (SAME, offset delta=32) 
Modified code: Code(maxStack = 4, maxLocals = 6, code_length = 45)
0:    getstatic		daikon.chicory.Runtime.nonce Ljava/util/concurrent/atomic/AtomicInteger; (109)
3:    invokevirtual	java.util.concurrent.atomic.AtomicInteger.getAndIncrement ()I (115)
6:    istore		%5
8:    aload_0
9:    iload		%5
11:   iconst_3
12:   iconst_2
13:   anewarray		<java.lang.Object> (8)
16:   dup
17:   iconst_0
18:   new		<daikon.chicory.Runtime$DoubleWrap> (128)
21:   dup
22:   dload_1
23:   invokespecial	daikon.chicory.Runtime$DoubleWrap.<init> (D)V (131)
26:   aastore
27:   dup
28:   iconst_1
29:   new		<daikon.chicory.Runtime$DoubleWrap> (128)
32:   dup
33:   dload_3
34:   invokespecial	daikon.chicory.Runtime$DoubleWrap.<init> (D)V (131)
37:   aastore
38:   invokestatic	daikon.chicory.Runtime.enter (Ljava/lang/Object;II[Ljava/lang/Object;)V (119)
41:   dload_1
42:   dload_3
43:   dmul
44:   dreturn

Attribute(s) = 
LocalVariableTable:
LocalVariable(startPc = 0, length = 45, index = 0:daikon.chicory.ChicoryTest this)
LocalVariable(startPc = 0, length = 45, index = 1:double d1)
LocalVariable(startPc = 0, length = 45, index = 3:double d2)
LocalVariable(startPc = 0, length = 45, index = 5:int this_invocation_nonce)
LineNumberTable:
LineNumber(0, 32)
Adding return local of type double

StackMap(Before insert_inst) 2 items:
@008 (APPEND 1, offset delta=8, locals={(type=Integer)}) 
@041 (SAME, offset delta=32) 
inst:   44: dreturn[175](1) 
targeter: LocalVariableGen(this, daikon.chicory.ChicoryTest,    0: getstatic[178](3) 109,   44: dreturn[175](1)) 
targeter: LocalVariableGen(this_invocation_nonce, int,    0: getstatic[178](3) 109,   44: dreturn[175](1)) 
targeter: LocalVariableGen(d2, double,    0: getstatic[178](3) 109,   44: dreturn[175](1)) 
targeter: LocalVariableGen(d1, double,    0: getstatic[178](3) 109,   44: dreturn[175](1)) 
targeter: LocalVariableGen(return__$trace2_val, double,    0: getstatic[178](3) 109,   44: dreturn[175](1)) 
  insert_inst: 27
   0: dup2[92](1)
   1: dstore[57](2) 6
   3: aload_0[42](1)
   4: iload[21](2) 5
   6: iconst_3[6](1)
   7: iconst_2[5](1)
   8: anewarray[189](3) 8
  11: dup[89](1)
  12: iconst_0[3](1)
  13: new[187](3) 128
  16: dup[89](1)
  17: dload_1[39](1)
  18: invokespecial[183](3) 131
  21: aastore[83](1)
  22: dup[89](1)
  23: iconst_1[4](1)
  24: new[187](3) 128
  27: dup[89](1)
  28: dload_3[41](1)
  29: invokespecial[183](3) 131
  32: aastore[83](1)
  33: new[187](3) 128
  36: dup[89](1)
  37: dload[24](2) 6
  39: invokespecial[183](3) 131
  42: bipush[16](2) 32
  44: invokestatic[184](3) 123

  ih:   44: dreturn[175](1)

StackMap(After updateStackMapOffset) 2 items:
@008 (APPEND 1, offset delta=8, locals={(type=Integer)}) 
@041 (SAME, offset delta=32) 
inst:   44: dup2[92](1) 
inst:   45: dstore[57](2) 6 
inst:   47: aload_0[42](1) 
inst:   48: iload[21](2) 5 
inst:   50: iconst_3[6](1) 
inst:   51: iconst_2[5](1) 
inst:   52: anewarray[189](3) 8 
inst:   55: dup[89](1) 
inst:   56: iconst_0[3](1) 
inst:   57: new[187](3) 128 
inst:   60: dup[89](1) 
inst:   61: dload_1[39](1) 
inst:   62: invokespecial[183](3) 131 
inst:   65: aastore[83](1) 
inst:   66: dup[89](1) 
inst:   67: iconst_1[4](1) 
inst:   68: new[187](3) 128 
inst:   71: dup[89](1) 
inst:   72: dload_3[41](1) 
inst:   73: invokespecial[183](3) 131 
inst:   76: aastore[83](1) 
inst:   77: new[187](3) 128 
inst:   80: dup[89](1) 
inst:   81: dload[24](2) 6 
inst:   83: invokespecial[183](3) 131 
inst:   86: bipush[16](2) 32 
inst:   88: invokestatic[184](3) 123 
inst:   91: dreturn[175](1) 
targeter: LocalVariableGen(this, daikon.chicory.ChicoryTest,    0: getstatic[178](3) 109,   91: dreturn[175](1)) 
targeter: LocalVariableGen(this_invocation_nonce, int,    0: getstatic[178](3) 109,   91: dreturn[175](1)) 
targeter: LocalVariableGen(d2, double,    0: getstatic[178](3) 109,   91: dreturn[175](1)) 
targeter: LocalVariableGen(d1, double,    0: getstatic[178](3) 109,   91: dreturn[175](1)) 
targeter: LocalVariableGen(return__$trace2_val, double,    0: getstatic[178](3) 109,   91: dreturn[175](1)) 

StackMap(Final) 2 items:
@008 (APPEND 1, offset delta=8, locals={(type=Integer)}) 
@041 (SAME, offset delta=32) 
Modified code: Code(maxStack = 12, maxLocals = 8, code_length = 92)
0:    getstatic		daikon.chicory.Runtime.nonce Ljava/util/concurrent/atomic/AtomicInteger; (109)
3:    invokevirtual	java.util.concurrent.atomic.AtomicInteger.getAndIncrement ()I (115)
6:    istore		%5
8:    aload_0
9:    iload		%5
11:   iconst_3
12:   iconst_2
13:   anewarray		<java.lang.Object> (8)
16:   dup
17:   iconst_0
18:   new		<daikon.chicory.Runtime$DoubleWrap> (128)
21:   dup
22:   dload_1
23:   invokespecial	daikon.chicory.Runtime$DoubleWrap.<init> (D)V (131)
26:   aastore
27:   dup
28:   iconst_1
29:   new		<daikon.chicory.Runtime$DoubleWrap> (128)
32:   dup
33:   dload_3
34:   invokespecial	daikon.chicory.Runtime$DoubleWrap.<init> (D)V (131)
37:   aastore
38:   invokestatic	daikon.chicory.Runtime.enter (Ljava/lang/Object;II[Ljava/lang/Object;)V (119)
41:   dload_1
42:   dload_3
43:   dmul
44:   dup2
45:   dstore		%6
47:   aload_0
48:   iload		%5
50:   iconst_3
51:   iconst_2
52:   anewarray		<java.lang.Object> (8)
55:   dup
56:   iconst_0
57:   new		<daikon.chicory.Runtime$DoubleWrap> (128)
60:   dup
61:   dload_1
62:   invokespecial	daikon.chicory.Runtime$DoubleWrap.<init> (D)V (131)
65:   aastore
66:   dup
67:   iconst_1
68:   new		<daikon.chicory.Runtime$DoubleWrap> (128)
71:   dup
72:   dload_3
73:   invokespecial	daikon.chicory.Runtime$DoubleWrap.<init> (D)V (131)
76:   aastore
77:   new		<daikon.chicory.Runtime$DoubleWrap> (128)
80:   dup
81:   dload		%6
83:   invokespecial	daikon.chicory.Runtime$DoubleWrap.<init> (D)V (131)
86:   bipush		32
88:   invokestatic	daikon.chicory.Runtime.exit (Ljava/lang/Object;II[Ljava/lang/Object;Ljava/lang/Object;I)V (123)
91:   dreturn

Attribute(s) = 
StackMapTable:
StackMap(
@008 (APPEND 1, offset delta=8, locals={(type=Integer)}), 
@041 (SAME, offset delta=32))
LocalVariableTable:
LocalVariable(startPc = 0, length = 92, index = 0:daikon.chicory.ChicoryTest this)
LocalVariable(startPc = 0, length = 92, index = 1:double d1)
LocalVariable(startPc = 0, length = 92, index = 3:double d2)
LocalVariable(startPc = 0, length = 92, index = 5:int this_invocation_nonce)
LocalVariable(startPc = 0, length = 92, index = 6:double return__$trace2_val)
LineNumberTable:
LineNumber(0, 32)
Attribute Index: 57 Name: StackMapTable
Attribute Index: 34 Name: LocalVariableTable
Attribute Index: 33 Name: LineNumberTable

Method = public int sample(int myint)
arg_types(1): int 
arg_names(1): arg0 
localvars(3): this myint my_d 
Original code: Code(maxStack = 3, maxLocals = 4, code_length = 27)
0:    aload_0
1:    getfield		daikon.chicory.ChicoryTest.t1 I (2)
4:    i2d
5:    dstore_2
6:    aload_0
7:    getfield		daikon.chicory.ChicoryTest.t1 I (2)
10:   bipush		6
12:   if_icmpne		#21
15:   dload_2
16:   d2i
17:   bipush		7
19:   iadd
20:   ireturn
21:   bipush		7
23:   dload_2
24:   d2i
25:   imul
26:   ireturn

Attribute(s) = 
StackMapTable:
StackMap(
@021 (APPEND 1, offset delta=21, locals={(type=Double)}))
LocalVariableTable:
LocalVariable(startPc = 0, length = 27, index = 0:daikon.chicory.ChicoryTest this)
LocalVariable(startPc = 0, length = 27, index = 1:int myint)
LocalVariable(startPc = 6, length = 21, index = 2:double my_d)
LineNumberTable:
LineNumber(0, 37), LineNumber(6, 39), LineNumber(15, 40), LineNumber(21, 42)

Attribute tag: 11 length: 6 nameIndex: 57

StackMap(Original) 1 items:
@021 (APPEND 1, offset delta=21, locals={(type=Double)}) 
Added <this> 0: this, daikon.chicory.ChicoryTest
Added param  1: myint, int
Added local  2: my_d, double
create_method_info1 1
arg: arg0
create_method_info2 1
arg: myint
Looking for exit points in sample
Exit at line 40
Exit at line 42

StackMap(After create_method_info) 1 items:
@021 (APPEND 1, offset delta=21, locals={(type=Double)}) 
Added local  2: this_invocation_nonce, int
New LocalVariableTable:
LocalVariable(startPc = 0, length = 27, index = 0:daikon.chicory.ChicoryTest this)
LocalVariable(startPc = 0, length = 27, index = 1:int myint)
LocalVariable(startPc = 0, length = 27, index = 2:int this_invocation_nonce)
LocalVariable(startPc = 6, length = 20, index = 3:double my_d)

StackMap(After cln) 1 items:
@021 (APPEND 1, offset delta=21, locals={(type=Double)}) 
Modified code: Code(maxStack = 3, maxLocals = 5, code_length = 27)
0:    aload_0
1:    getfield		daikon.chicory.ChicoryTest.t1 I (2)
4:    i2d
5:    dstore_3
6:    aload_0
7:    getfield		daikon.chicory.ChicoryTest.t1 I (2)
10:   bipush		6
12:   if_icmpne		#21
15:   dload_3
16:   d2i
17:   bipush		7
19:   iadd
20:   ireturn
21:   bipush		7
23:   dload_3
24:   d2i
25:   imul
26:   ireturn

Attribute(s) = 
LocalVariableTable:
LocalVariable(startPc = 0, length = 27, index = 0:daikon.chicory.ChicoryTest this)
LocalVariable(startPc = 0, length = 27, index = 1:int myint)
LocalVariable(startPc = 0, length = 27, index = 2:int this_invocation_nonce)
LocalVariable(startPc = 6, length = 20, index = 3:double my_d)
LineNumberTable:
LineNumber(0, 37), LineNumber(6, 39), LineNumber(15, 40), LineNumber(21, 42)

StackMap(After add_entry_instrumentation) 3 items:
@007 (APPEND 1, offset delta=7, locals={(type=Integer)}) 
@028 (SAME, offset delta=20) 
@049 (APPEND 1, offset delta=20, locals={(type=Double)}) 
Modified code: Code(maxStack = 3, maxLocals = 5, code_length = 55)
0:    getstatic		daikon.chicory.Runtime.nonce Ljava/util/concurrent/atomic/AtomicInteger; (109)
3:    invokevirtual	java.util.concurrent.atomic.AtomicInteger.getAndIncrement ()I (115)
6:    istore_2
7:    aload_0
8:    iload_2
9:    iconst_4
10:   iconst_1
11:   anewarray		<java.lang.Object> (8)
14:   dup
15:   iconst_0
16:   new		<daikon.chicory.Runtime$IntWrap> (133)
19:   dup
20:   iload_1
21:   invokespecial	daikon.chicory.Runtime$IntWrap.<init> (I)V (136)
24:   aastore
25:   invokestatic	daikon.chicory.Runtime.enter (Ljava/lang/Object;II[Ljava/lang/Object;)V (119)
28:   aload_0
29:   getfield		daikon.chicory.ChicoryTest.t1 I (2)
32:   i2d
33:   dstore_3
34:   aload_0
35:   getfield		daikon.chicory.ChicoryTest.t1 I (2)
38:   bipush		6
40:   if_icmpne		#49
43:   dload_3
44:   d2i
45:   bipush		7
47:   iadd
48:   ireturn
49:   bipush		7
51:   dload_3
52:   d2i
53:   imul
54:   ireturn

Attribute(s) = 
LocalVariableTable:
LocalVariable(startPc = 0, length = 55, index = 0:daikon.chicory.ChicoryTest this)
LocalVariable(startPc = 0, length = 55, index = 1:int myint)
LocalVariable(startPc = 0, length = 55, index = 2:int this_invocation_nonce)
LocalVariable(startPc = 34, length = 20, index = 3:double my_d)
LineNumberTable:
LineNumber(0, 37), LineNumber(34, 39), LineNumber(43, 40), LineNumber(49, 42)
Adding return local of type int

StackMap(Before insert_inst) 3 items:
@007 (APPEND 1, offset delta=7, locals={(type=Integer)}) 
@028 (SAME, offset delta=20) 
@049 (APPEND 1, offset delta=20, locals={(type=Double)}) 
inst:   48: ireturn[172](1) 
inst:   49: bipush[16](2) 7 
targeter: if_icmpne[160](3) -> 49 
targeter: org.apache.bcel.generic.LineNumberGen@69d9c55 
inst:   51: dload_3[41](1) 
inst:   52: d2i[142](1) 
inst:   53: imul[104](1) 
inst:   54: ireturn[172](1) 
targeter: LocalVariableGen(this, daikon.chicory.ChicoryTest,    0: getstatic[178](3) 109,   54: ireturn[172](1)) 
targeter: LocalVariableGen(myint, int,    0: getstatic[178](3) 109,   54: ireturn[172](1)) 
targeter: LocalVariableGen(this_invocation_nonce, int,    0: getstatic[178](3) 109,   54: ireturn[172](1)) 
targeter: LocalVariableGen(return__$trace2_val, int,    0: getstatic[178](3) 109,   54: ireturn[172](1)) 
targeter: LocalVariableGen(my_d, double,   34: aload_0[42](1),   54: ireturn[172](1)) 
  insert_inst: 20
   0: dup[89](1)
   1: istore[54](2) 5
   3: aload_0[42](1)
   4: iload_2[28](1)
   5: iconst_4[7](1)
   6: iconst_1[4](1)
   7: anewarray[189](3) 8
  10: dup[89](1)
  11: iconst_0[3](1)
  12: new[187](3) 133
  15: dup[89](1)
  16: iload_1[27](1)
  17: invokespecial[183](3) 136
  20: aastore[83](1)
  21: new[187](3) 133
  24: dup[89](1)
  25: iload[21](2) 5
  27: invokespecial[183](3) 136
  30: bipush[16](2) 40
  32: invokestatic[184](3) 123

  ih:   48: ireturn[172](1)

StackMap(After updateStackMapOffset) 3 items:
@007 (APPEND 1, offset delta=7, locals={(type=Integer)}) 
@028 (SAME, offset delta=20) 
@084 (APPEND 1, offset delta=55, locals={(type=Double)}) 
inst:   48: dup[89](1) 
inst:   49: istore[54](2) 5 
inst:   51: aload_0[42](1) 
inst:   52: iload_2[28](1) 
inst:   53: iconst_4[7](1) 
inst:   54: iconst_1[4](1) 
inst:   55: anewarray[189](3) 8 
inst:   58: dup[89](1) 
inst:   59: iconst_0[3](1) 
inst:   60: new[187](3) 133 
inst:   63: dup[89](1) 
inst:   64: iload_1[27](1) 
inst:   65: invokespecial[183](3) 136 
inst:   68: aastore[83](1) 
inst:   69: new[187](3) 133 
inst:   72: dup[89](1) 
inst:   73: iload[21](2) 5 
inst:   75: invokespecial[183](3) 136 
inst:   78: bipush[16](2) 40 
inst:   80: invokestatic[184](3) 123 
inst:   83: ireturn[172](1) 
inst:   84: bipush[16](2) 7 
targeter: if_icmpne[160](3) -> 84 
targeter: org.apache.bcel.generic.LineNumberGen@69d9c55 
inst:   86: dload_3[41](1) 
inst:   87: d2i[142](1) 
inst:   88: imul[104](1) 
inst:   89: ireturn[172](1) 
targeter: LocalVariableGen(this, daikon.chicory.ChicoryTest,    0: getstatic[178](3) 109,   89: ireturn[172](1)) 
targeter: LocalVariableGen(myint, int,    0: getstatic[178](3) 109,   89: ireturn[172](1)) 
targeter: LocalVariableGen(this_invocation_nonce, int,    0: getstatic[178](3) 109,   89: ireturn[172](1)) 
targeter: LocalVariableGen(return__$trace2_val, int,    0: getstatic[178](3) 109,   89: ireturn[172](1)) 
targeter: LocalVariableGen(my_d, double,   34: aload_0[42](1),   89: ireturn[172](1)) 

StackMap(Before insert_inst) 3 items:
@007 (APPEND 1, offset delta=7, locals={(type=Integer)}) 
@028 (SAME, offset delta=20) 
@084 (APPEND 1, offset delta=55, locals={(type=Double)}) 
inst:   89: ireturn[172](1) 
targeter: LocalVariableGen(this, daikon.chicory.ChicoryTest,    0: getstatic[178](3) 109,   89: ireturn[172](1)) 
targeter: LocalVariableGen(myint, int,    0: getstatic[178](3) 109,   89: ireturn[172](1)) 
targeter: LocalVariableGen(this_invocation_nonce, int,    0: getstatic[178](3) 109,   89: ireturn[172](1)) 
targeter: LocalVariableGen(return__$trace2_val, int,    0: getstatic[178](3) 109,   89: ireturn[172](1)) 
targeter: LocalVariableGen(my_d, double,   34: aload_0[42](1),   89: ireturn[172](1)) 
  insert_inst: 20
   0: dup[89](1)
   1: istore[54](2) 5
   3: aload_0[42](1)
   4: iload_2[28](1)
   5: iconst_4[7](1)
   6: iconst_1[4](1)
   7: anewarray[189](3) 8
  10: dup[89](1)
  11: iconst_0[3](1)
  12: new[187](3) 133
  15: dup[89](1)
  16: iload_1[27](1)
  17: invokespecial[183](3) 136
  20: aastore[83](1)
  21: new[187](3) 133
  24: dup[89](1)
  25: iload[21](2) 5
  27: invokespecial[183](3) 136
  30: bipush[16](2) 42
  32: invokestatic[184](3) 123

  ih:   89: ireturn[172](1)

StackMap(After updateStackMapOffset) 3 items:
@007 (APPEND 1, offset delta=7, locals={(type=Integer)}) 
@028 (SAME, offset delta=20) 
@084 (APPEND 1, offset delta=55, locals={(type=Double)}) 
inst:   89: dup[89](1) 
inst:   90: istore[54](2) 5 
inst:   92: aload_0[42](1) 
inst:   93: iload_2[28](1) 
inst:   94: iconst_4[7](1) 
inst:   95: iconst_1[4](1) 
inst:   96: anewarray[189](3) 8 
inst:   99: dup[89](1) 
inst:  100: iconst_0[3](1) 
inst:  101: new[187](3) 133 
inst:  104: dup[89](1) 
inst:  105: iload_1[27](1) 
inst:  106: invokespecial[183](3) 136 
inst:  109: aastore[83](1) 
inst:  110: new[187](3) 133 
inst:  113: dup[89](1) 
inst:  114: iload[21](2) 5 
inst:  116: invokespecial[183](3) 136 
inst:  119: bipush[16](2) 42 
inst:  121: invokestatic[184](3) 123 
inst:  124: ireturn[172](1) 
targeter: LocalVariableGen(this, daikon.chicory.ChicoryTest,    0: getstatic[178](3) 109,  124: ireturn[172](1)) 
targeter: LocalVariableGen(myint, int,    0: getstatic[178](3) 109,  124: ireturn[172](1)) 
targeter: LocalVariableGen(this_invocation_nonce, int,    0: getstatic[178](3) 109,  124: ireturn[172](1)) 
targeter: LocalVariableGen(return__$trace2_val, int,    0: getstatic[178](3) 109,  124: ireturn[172](1)) 
targeter: LocalVariableGen(my_d, double,   34: aload_0[42](1),  124: ireturn[172](1)) 

StackMap(Final) 3 items:
@007 (APPEND 1, offset delta=7, locals={(type=Integer)}) 
@028 (SAME, offset delta=20) 
@084 (APPEND 1, offset delta=55, locals={(type=Double)}) 
Modified code: Code(maxStack = 10, maxLocals = 6, code_length = 125)
0:    getstatic		daikon.chicory.Runtime.nonce Ljava/util/concurrent/atomic/AtomicInteger; (109)
3:    invokevirtual	java.util.concurrent.atomic.AtomicInteger.getAndIncrement ()I (115)
6:    istore_2
7:    aload_0
8:    iload_2
9:    iconst_4
10:   iconst_1
11:   anewarray		<java.lang.Object> (8)
14:   dup
15:   iconst_0
16:   new		<daikon.chicory.Runtime$IntWrap> (133)
19:   dup
20:   iload_1
21:   invokespecial	daikon.chicory.Runtime$IntWrap.<init> (I)V (136)
24:   aastore
25:   invokestatic	daikon.chicory.Runtime.enter (Ljava/lang/Object;II[Ljava/lang/Object;)V (119)
28:   aload_0
29:   getfield		daikon.chicory.ChicoryTest.t1 I (2)
32:   i2d
33:   dstore_3
34:   aload_0
35:   getfield		daikon.chicory.ChicoryTest.t1 I (2)
38:   bipush		6
40:   if_icmpne		#84
43:   dload_3
44:   d2i
45:   bipush		7
47:   iadd
48:   dup
49:   istore		%5
51:   aload_0
52:   iload_2
53:   iconst_4
54:   iconst_1
55:   anewarray		<java.lang.Object> (8)
58:   dup
59:   iconst_0
60:   new		<daikon.chicory.Runtime$IntWrap> (133)
63:   dup
64:   iload_1
65:   invokespecial	daikon.chicory.Runtime$IntWrap.<init> (I)V (136)
68:   aastore
69:   new		<daikon.chicory.Runtime$IntWrap> (133)
72:   dup
73:   iload		%5
75:   invokespecial	daikon.chicory.Runtime$IntWrap.<init> (I)V (136)
78:   bipush		40
80:   invokestatic	daikon.chicory.Runtime.exit (Ljava/lang/Object;II[Ljava/lang/Object;Ljava/lang/Object;I)V (123)
83:   ireturn
84:   bipush		7
86:   dload_3
87:   d2i
88:   imul
89:   dup
90:   istore		%5
92:   aload_0
93:   iload_2
94:   iconst_4
95:   iconst_1
96:   anewarray		<java.lang.Object> (8)
99:   dup
100:  iconst_0
101:  new		<daikon.chicory.Runtime$IntWrap> (133)
104:  dup
105:  iload_1
106:  invokespecial	daikon.chicory.Runtime$IntWrap.<init> (I)V (136)
109:  aastore
110:  new		<daikon.chicory.Runtime$IntWrap> (133)
113:  dup
114:  iload		%5
116:  invokespecial	daikon.chicory.Runtime$IntWrap.<init> (I)V (136)
119:  bipush		42
121:  invokestatic	daikon.chicory.Runtime.exit (Ljava/lang/Object;II[Ljava/lang/Object;Ljava/lang/Object;I)V (123)
124:  ireturn

Attribute(s) = 
StackMapTable:
StackMap(
@007 (APPEND 1, offset delta=7, locals={(type=Integer)}), 
@028 (SAME, offset delta=20), 
@084 (APPEND 1, offset delta=55, locals={(type=Double)}))
LocalVariableTable:
LocalVariable(startPc = 0, length = 125, index = 0:daikon.chicory.ChicoryTest this)
LocalVariable(startPc = 0, length = 125, index = 1:int myint)
LocalVariable(startPc = 0, length = 125, index = 2:int this_invocation_nonce)
LocalVariable(startPc = 34, length = 90, index = 3:double my_d)
LocalVariable(startPc = 0, length = 125, index = 5:int return__$trace2_val)
LineNumberTable:
LineNumber(0, 37), LineNumber(34, 39), LineNumber(43, 40), LineNumber(84, 42)
Attribute Index: 57 Name: StackMapTable
Attribute Index: 34 Name: LocalVariableTable
Attribute Index: 33 Name: LineNumberTable

Method = public daikon.chicory.ChicoryTest sample1()
arg_types(0): 
arg_names(0): 
localvars(2): this test1 
Original code: Code(maxStack = 2, maxLocals = 2, code_length = 16)
0:    new		<daikon.chicory.ChicoryTest> (3)
3:    dup
4:    invokespecial	daikon.chicory.ChicoryTest.<init> ()V (4)
7:    astore_1
8:    aload_1
9:    bipush		32
11:   putfield		daikon.chicory.ChicoryTest.t1 I (2)
14:   aload_1
15:   areturn

Attribute(s) = 
LocalVariableTable:
LocalVariable(startPc = 0, length = 16, index = 0:daikon.chicory.ChicoryTest this)
LocalVariable(startPc = 8, length = 8, index = 1:daikon.chicory.ChicoryTest test1)
LineNumberTable:
LineNumber(0, 48), LineNumber(8, 49), LineNumber(14, 50)


StackMap(Original) 0 items:
Added <this> 0: this, daikon.chicory.ChicoryTest
Added local  1: test1, daikon.chicory.ChicoryTest
create_method_info1 0
create_method_info2 0
Looking for exit points in sample1
Exit at line 50

StackMap(After create_method_info) 0 items:
Added local  1: this_invocation_nonce, int
New LocalVariableTable:
LocalVariable(startPc = 0, length = 16, index = 0:daikon.chicory.ChicoryTest this)
LocalVariable(startPc = 0, length = 16, index = 1:int this_invocation_nonce)
LocalVariable(startPc = 8, length = 7, index = 2:daikon.chicory.ChicoryTest test1)

StackMap(After cln) 0 items:
Modified code: Code(maxStack = 2, maxLocals = 3, code_length = 16)
0:    new		<daikon.chicory.ChicoryTest> (3)
3:    dup
4:    invokespecial	daikon.chicory.ChicoryTest.<init> ()V (4)
7:    astore_2
8:    aload_2
9:    bipush		32
11:   putfield		daikon.chicory.ChicoryTest.t1 I (2)
14:   aload_2
15:   areturn

Attribute(s) = 
LocalVariableTable:
LocalVariable(startPc = 0, length = 16, index = 0:daikon.chicory.ChicoryTest this)
LocalVariable(startPc = 0, length = 16, index = 1:int this_invocation_nonce)
LocalVariable(startPc = 8, length = 7, index = 2:daikon.chicory.ChicoryTest test1)
LineNumberTable:
LineNumber(0, 48), LineNumber(8, 49), LineNumber(14, 50)

StackMap(After add_entry_instrumentation) 2 items:
@007 (APPEND 1, offset delta=7, locals={(type=Integer)}) 
@017 (SAME, offset delta=9) 
Modified code: Code(maxStack = 2, maxLocals = 3, code_length = 33)
0:    getstatic		daikon.chicory.Runtime.nonce Ljava/util/concurrent/atomic/AtomicInteger; (109)
3:    invokevirtual	java.util.concurrent.atomic.AtomicInteger.getAndIncrement ()I (115)
6:    istore_1
7:    aload_0
8:    iload_1
9:    iconst_5
10:   iconst_0
11:   anewarray		<java.lang.Object> (8)
14:   invokestatic	daikon.chicory.Runtime.enter (Ljava/lang/Object;II[Ljava/lang/Object;)V (119)
17:   new		<daikon.chicory.ChicoryTest> (3)
20:   dup
21:   invokespecial	daikon.chicory.ChicoryTest.<init> ()V (4)
24:   astore_2
25:   aload_2
26:   bipush		32
28:   putfield		daikon.chicory.ChicoryTest.t1 I (2)
31:   aload_2
32:   areturn

Attribute(s) = 
LocalVariableTable:
LocalVariable(startPc = 0, length = 33, index = 0:daikon.chicory.ChicoryTest this)
LocalVariable(startPc = 0, length = 33, index = 1:int this_invocation_nonce)
LocalVariable(startPc = 25, length = 7, index = 2:daikon.chicory.ChicoryTest test1)
LineNumberTable:
LineNumber(0, 48), LineNumber(25, 49), LineNumber(31, 50)
Adding return local of type daikon.chicory.ChicoryTest

StackMap(Before insert_inst) 2 items:
@007 (APPEND 1, offset delta=7, locals={(type=Integer)}) 
@017 (SAME, offset delta=9) 
inst:   32: areturn[176](1) 
targeter: LocalVariableGen(return__$trace2_val, daikon.chicory.ChicoryTest,    0: getstatic[178](3) 109,   32: areturn[176](1)) 
targeter: LocalVariableGen(this, daikon.chicory.ChicoryTest,    0: getstatic[178](3) 109,   32: areturn[176](1)) 
targeter: LocalVariableGen(this_invocation_nonce, int,    0: getstatic[178](3) 109,   32: areturn[176](1)) 
targeter: LocalVariableGen(test1, daikon.chicory.ChicoryTest,   25: aload_2[44](1),   32: areturn[176](1)) 
  insert_inst: 10
   0: dup[89](1)
   1: astore_3[78](1)
   2: aload_0[42](1)
   3: iload_1[27](1)
   4: iconst_5[8](1)
   5: iconst_0[3](1)
   6: anewarray[189](3) 8
   9: aload_3[45](1)
  10: bipush[16](2) 50
  12: invokestatic[184](3) 123

  ih:   32: areturn[176](1)

StackMap(After updateStackMapOffset) 2 items:
@007 (APPEND 1, offset delta=7, locals={(type=Integer)}) 
@017 (SAME, offset delta=9) 
inst:   32: dup[89](1) 
inst:   33: astore_3[78](1) 
inst:   34: aload_0[42](1) 
inst:   35: iload_1[27](1) 
inst:   36: iconst_5[8](1) 
inst:   37: iconst_0[3](1) 
inst:   38: anewarray[189](3) 8 
inst:   41: aload_3[45](1) 
inst:   42: bipush[16](2) 50 
inst:   44: invokestatic[184](3) 123 
inst:   47: areturn[176](1) 
targeter: LocalVariableGen(return__$trace2_val, daikon.chicory.ChicoryTest,    0: getstatic[178](3) 109,   47: areturn[176](1)) 
targeter: LocalVariableGen(this, daikon.chicory.ChicoryTest,    0: getstatic[178](3) 109,   47: areturn[176](1)) 
targeter: LocalVariableGen(this_invocation_nonce, int,    0: getstatic[178](3) 109,   47: areturn[176](1)) 
targeter: LocalVariableGen(test1, daikon.chicory.ChicoryTest,   25: aload_2[44](1),   47: areturn[176](1)) 

StackMap(Final) 2 items:
@007 (APPEND 1, offset delta=7, locals={(type=Integer)}) 
@017 (SAME, offset delta=9) 
Modified code: Code(maxStack = 7, maxLocals = 4, code_length = 48)
0:    getstatic		daikon.chicory.Runtime.nonce Ljava/util/concurrent/atomic/AtomicInteger; (109)
3:    invokevirtual	java.util.concurrent.atomic.AtomicInteger.getAndIncrement ()I (115)
6:    istore_1
7:    aload_0
8:    iload_1
9:    iconst_5
10:   iconst_0
11:   anewarray		<java.lang.Object> (8)
14:   invokestatic	daikon.chicory.Runtime.enter (Ljava/lang/Object;II[Ljava/lang/Object;)V (119)
17:   new		<daikon.chicory.ChicoryTest> (3)
20:   dup
21:   invokespecial	daikon.chicory.ChicoryTest.<init> ()V (4)
24:   astore_2
25:   aload_2
26:   bipush		32
28:   putfield		daikon.chicory.ChicoryTest.t1 I (2)
31:   aload_2
32:   dup
33:   astore_3
34:   aload_0
35:   iload_1
36:   iconst_5
37:   iconst_0
38:   anewarray		<java.lang.Object> (8)
41:   aload_3
42:   bipush		50
44:   invokestatic	daikon.chicory.Runtime.exit (Ljava/lang/Object;II[Ljava/lang/Object;Ljava/lang/Object;I)V (123)
47:   areturn

Attribute(s) = 
StackMapTable:
StackMap(
@007 (APPEND 1, offset delta=7, locals={(type=Integer)}), 
@017 (SAME, offset delta=9))
LocalVariableTable:
LocalVariable(startPc = 0, length = 48, index = 0:daikon.chicory.ChicoryTest this)
LocalVariable(startPc = 0, length = 48, index = 1:int this_invocation_nonce)
LocalVariable(startPc = 25, length = 22, index = 2:daikon.chicory.ChicoryTest test1)
LocalVariable(startPc = 0, length = 48, index = 3:daikon.chicory.ChicoryTest return__$trace2_val)
LineNumberTable:
LineNumber(0, 48), LineNumber(25, 49), LineNumber(31, 50)
Attribute Index: 57 Name: StackMapTable
Attribute Index: 34 Name: LocalVariableTable
Attribute Index: 33 Name: LineNumberTable

Method = public double sample2()
arg_types(0): 
arg_names(0): 
localvars(1): this 
Original code: Code(maxStack = 2, maxLocals = 1, code_length = 17)
0:    aload_0
1:    getfield		daikon.chicory.ChicoryTest.t1 I (2)
4:    bipush		6
6:    if_icmpne		#13
9:    ldc2_w		5.43 (24)
12:   dreturn
13:   ldc2_w		62.4 (26)
16:   dreturn

Attribute(s) = 
StackMapTable:
StackMap(
@013 (SAME, offset delta=13))
LocalVariableTable:
LocalVariable(startPc = 0, length = 17, index = 0:daikon.chicory.ChicoryTest this)
LineNumberTable:
LineNumber(0, 55), LineNumber(9, 56), LineNumber(13, 58)

Attribute tag: 11 length: 3 nameIndex: 57

StackMap(Original) 1 items:
@013 (SAME, offset delta=13) 
Added <this> 0: this, daikon.chicory.ChicoryTest
create_method_info1 0
create_method_info2 0
Looking for exit points in sample2
Exit at line 56
Exit at line 58

StackMap(After create_method_info) 1 items:
@013 (SAME, offset delta=13) 
Added local  1: this_invocation_nonce, int
New LocalVariableTable:
LocalVariable(startPc = 0, length = 17, index = 0:daikon.chicory.ChicoryTest this)
LocalVariable(startPc = 0, length = 17, index = 1:int this_invocation_nonce)

StackMap(After cln) 1 items:
@013 (SAME, offset delta=13) 
Modified code: Code(maxStack = 2, maxLocals = 2, code_length = 17)
0:    aload_0
1:    getfield		daikon.chicory.ChicoryTest.t1 I (2)
4:    bipush		6
6:    if_icmpne		#13
9:    ldc2_w		5.43 (24)
12:   dreturn
13:   ldc2_w		62.4 (26)
16:   dreturn

Attribute(s) = 
LocalVariableTable:
LocalVariable(startPc = 0, length = 17, index = 0:daikon.chicory.ChicoryTest this)
LocalVariable(startPc = 0, length = 17, index = 1:int this_invocation_nonce)
LineNumberTable:
LineNumber(0, 55), LineNumber(9, 56), LineNumber(13, 58)

StackMap(After add_entry_instrumentation) 3 items:
@007 (APPEND 1, offset delta=7, locals={(type=Integer)}) 
@018 (SAME, offset delta=10) 
@031 (SAME, offset delta=12) 
Modified code: Code(maxStack = 2, maxLocals = 2, code_length = 35)
0:    getstatic		daikon.chicory.Runtime.nonce Ljava/util/concurrent/atomic/AtomicInteger; (109)
3:    invokevirtual	java.util.concurrent.atomic.AtomicInteger.getAndIncrement ()I (115)
6:    istore_1
7:    aload_0
8:    iload_1
9:    bipush		6
11:   iconst_0
12:   anewarray		<java.lang.Object> (8)
15:   invokestatic	daikon.chicory.Runtime.enter (Ljava/lang/Object;II[Ljava/lang/Object;)V (119)
18:   aload_0
19:   getfield		daikon.chicory.ChicoryTest.t1 I (2)
22:   bipush		6
24:   if_icmpne		#31
27:   ldc2_w		5.43 (24)
30:   dreturn
31:   ldc2_w		62.4 (26)
34:   dreturn

Attribute(s) = 
LocalVariableTable:
LocalVariable(startPc = 0, length = 35, index = 0:daikon.chicory.ChicoryTest this)
LocalVariable(startPc = 0, length = 35, index = 1:int this_invocation_nonce)
LineNumberTable:
LineNumber(0, 55), LineNumber(27, 56), LineNumber(31, 58)
Adding return local of type double

StackMap(Before insert_inst) 3 items:
@007 (APPEND 1, offset delta=7, locals={(type=Integer)}) 
@018 (SAME, offset delta=10) 
@031 (SAME, offset delta=12) 
inst:   30: dreturn[175](1) 
inst:   31: ldc2_w[20](3) 26 
targeter: if_icmpne[160](3) -> 31 
targeter: org.apache.bcel.generic.LineNumberGen@6574b225 
inst:   34: dreturn[175](1) 
targeter: LocalVariableGen(this, daikon.chicory.ChicoryTest,    0: getstatic[178](3) 109,   34: dreturn[175](1)) 
targeter: LocalVariableGen(this_invocation_nonce, int,    0: getstatic[178](3) 109,   34: dreturn[175](1)) 
targeter: LocalVariableGen(return__$trace2_val, double,    0: getstatic[178](3) 109,   34: dreturn[175](1)) 
  insert_inst: 13
   0: dup2[92](1)
   1: dstore_2[73](1)
   2: aload_0[42](1)
   3: iload_1[27](1)
   4: bipush[16](2) 6
   6: iconst_0[3](1)
   7: anewarray[189](3) 8
  10: new[187](3) 128
  13: dup[89](1)
  14: dload_2[40](1)
  15: invokespecial[183](3) 131
  18: bipush[16](2) 56
  20: invokestatic[184](3) 123

  ih:   30: dreturn[175](1)

StackMap(After updateStackMapOffset) 3 items:
@007 (APPEND 1, offset delta=7, locals={(type=Integer)}) 
@018 (SAME, offset delta=10) 
@054 (SAME, offset delta=35) 
inst:   30: dup2[92](1) 
inst:   31: dstore_2[73](1) 
inst:   32: aload_0[42](1) 
inst:   33: iload_1[27](1) 
inst:   34: bipush[16](2) 6 
inst:   36: iconst_0[3](1) 
inst:   37: anewarray[189](3) 8 
inst:   40: new[187](3) 128 
inst:   43: dup[89](1) 
inst:   44: dload_2[40](1) 
inst:   45: invokespecial[183](3) 131 
inst:   48: bipush[16](2) 56 
inst:   50: invokestatic[184](3) 123 
inst:   53: dreturn[175](1) 
inst:   54: ldc2_w[20](3) 26 
targeter: if_icmpne[160](3) -> 54 
targeter: org.apache.bcel.generic.LineNumberGen@6574b225 
inst:   57: dreturn[175](1) 
targeter: LocalVariableGen(this, daikon.chicory.ChicoryTest,    0: getstatic[178](3) 109,   57: dreturn[175](1)) 
targeter: LocalVariableGen(this_invocation_nonce, int,    0: getstatic[178](3) 109,   57: dreturn[175](1)) 
targeter: LocalVariableGen(return__$trace2_val, double,    0: getstatic[178](3) 109,   57: dreturn[175](1)) 

StackMap(Before insert_inst) 3 items:
@007 (APPEND 1, offset delta=7, locals={(type=Integer)}) 
@018 (SAME, offset delta=10) 
@054 (SAME, offset delta=35) 
inst:   57: dreturn[175](1) 
targeter: LocalVariableGen(this, daikon.chicory.ChicoryTest,    0: getstatic[178](3) 109,   57: dreturn[175](1)) 
targeter: LocalVariableGen(this_invocation_nonce, int,    0: getstatic[178](3) 109,   57: dreturn[175](1)) 
targeter: LocalVariableGen(return__$trace2_val, double,    0: getstatic[178](3) 109,   57: dreturn[175](1)) 
  insert_inst: 13
   0: dup2[92](1)
   1: dstore_2[73](1)
   2: aload_0[42](1)
   3: iload_1[27](1)
   4: bipush[16](2) 6
   6: iconst_0[3](1)
   7: anewarray[189](3) 8
  10: new[187](3) 128
  13: dup[89](1)
  14: dload_2[40](1)
  15: invokespecial[183](3) 131
  18: bipush[16](2) 58
  20: invokestatic[184](3) 123

  ih:   57: dreturn[175](1)

StackMap(After updateStackMapOffset) 3 items:
@007 (APPEND 1, offset delta=7, locals={(type=Integer)}) 
@018 (SAME, offset delta=10) 
@054 (SAME, offset delta=35) 
inst:   57: dup2[92](1) 
inst:   58: dstore_2[73](1) 
inst:   59: aload_0[42](1) 
inst:   60: iload_1[27](1) 
inst:   61: bipush[16](2) 6 
inst:   63: iconst_0[3](1) 
inst:   64: anewarray[189](3) 8 
inst:   67: new[187](3) 128 
inst:   70: dup[89](1) 
inst:   71: dload_2[40](1) 
inst:   72: invokespecial[183](3) 131 
inst:   75: bipush[16](2) 58 
inst:   77: invokestatic[184](3) 123 
inst:   80: dreturn[175](1) 
targeter: LocalVariableGen(this, daikon.chicory.ChicoryTest,    0: getstatic[178](3) 109,   80: dreturn[175](1)) 
targeter: LocalVariableGen(this_invocation_nonce, int,    0: getstatic[178](3) 109,   80: dreturn[175](1)) 
targeter: LocalVariableGen(return__$trace2_val, double,    0: getstatic[178](3) 109,   80: dreturn[175](1)) 

StackMap(Final) 3 items:
@007 (APPEND 1, offset delta=7, locals={(type=Integer)}) 
@018 (SAME, offset delta=10) 
@054 (SAME, offset delta=35) 
Modified code: Code(maxStack = 10, maxLocals = 4, code_length = 81)
0:    getstatic		daikon.chicory.Runtime.nonce Ljava/util/concurrent/atomic/AtomicInteger; (109)
3:    invokevirtual	java.util.concurrent.atomic.AtomicInteger.getAndIncrement ()I (115)
6:    istore_1
7:    aload_0
8:    iload_1
9:    bipush		6
11:   iconst_0
12:   anewarray		<java.lang.Object> (8)
15:   invokestatic	daikon.chicory.Runtime.enter (Ljava/lang/Object;II[Ljava/lang/Object;)V (119)
18:   aload_0
19:   getfield		daikon.chicory.ChicoryTest.t1 I (2)
22:   bipush		6
24:   if_icmpne		#54
27:   ldc2_w		5.43 (24)
30:   dup2
31:   dstore_2
32:   aload_0
33:   iload_1
34:   bipush		6
36:   iconst_0
37:   anewarray		<java.lang.Object> (8)
40:   new		<daikon.chicory.Runtime$DoubleWrap> (128)
43:   dup
44:   dload_2
45:   invokespecial	daikon.chicory.Runtime$DoubleWrap.<init> (D)V (131)
48:   bipush		56
50:   invokestatic	daikon.chicory.Runtime.exit (Ljava/lang/Object;II[Ljava/lang/Object;Ljava/lang/Object;I)V (123)
53:   dreturn
54:   ldc2_w		62.4 (26)
57:   dup2
58:   dstore_2
59:   aload_0
60:   iload_1
61:   bipush		6
63:   iconst_0
64:   anewarray		<java.lang.Object> (8)
67:   new		<daikon.chicory.Runtime$DoubleWrap> (128)
70:   dup
71:   dload_2
72:   invokespecial	daikon.chicory.Runtime$DoubleWrap.<init> (D)V (131)
75:   bipush		58
77:   invokestatic	daikon.chicory.Runtime.exit (Ljava/lang/Object;II[Ljava/lang/Object;Ljava/lang/Object;I)V (123)
80:   dreturn

Attribute(s) = 
StackMapTable:
StackMap(
@007 (APPEND 1, offset delta=7, locals={(type=Integer)}), 
@018 (SAME, offset delta=10), 
@054 (SAME, offset delta=35))
LocalVariableTable:
LocalVariable(startPc = 0, length = 81, index = 0:daikon.chicory.ChicoryTest this)
LocalVariable(startPc = 0, length = 81, index = 1:int this_invocation_nonce)
LocalVariable(startPc = 0, length = 81, index = 2:double return__$trace2_val)
LineNumberTable:
LineNumber(0, 55), LineNumber(27, 56), LineNumber(54, 58)
Attribute Index: 57 Name: StackMapTable
Attribute Index: 34 Name: LocalVariableTable
Attribute Index: 33 Name: LineNumberTable
Dumping daikon.chicory.ChicoryTest to /tmp/chicory-debug3155414611702597785/daikon.chicory.ChicoryTest.class
sample return [35]   = 35
sample return [32]   = 32
sample return [62.4] = 62.4
